LICENSE
README.rst
setup.py
cravat/__init__.py
cravat/admin_util.py
cravat/aggregator.py
cravat/annotator_options.py
cravat/base_annotator.py
cravat/base_commonmodule.py
cravat/base_converter.py
cravat/base_mapper.py
cravat/base_postaggregator.py
cravat/base_summarizer.py
cravat/config_loader.py
cravat/constants.py
cravat/cravat-system.template.yml
cravat/cravat.yml
cravat/cravat_admin.py
cravat/cravat_class.py
cravat/cravat_convert.py
cravat/cravat_filter.py
cravat/cravat_metrics.py
cravat/cravat_pack.py
cravat/cravat_report.py
cravat/cravat_test.py
cravat/cravat_util.py
cravat/cravat_web.py
cravat/example_input
cravat/exceptions.py
cravat/inout.py
cravat/mp_runners.py
cravat/oc.py
cravat/runcravat.py
cravat/store_utils.py
cravat/util.py
cravat/vcfanno.py
cravat/wincravat.pyw
cravat/annotator_template/annotator_template.md
cravat/annotator_template/annotator_template.py
cravat/annotator_template/annotator_template.yml
cravat/annotator_template/data/annotator_template.sqlite
cravat/liftover/hg18ToHg38.over.chain
cravat/liftover/hg19ToHg38.over.chain
cravat/webresult/__init__.py
cravat/webresult/email.png
cravat/webresult/favicon.ico
cravat/webresult/favicon.png
cravat/webresult/index.html
cravat/webresult/jsonreporter.py
cravat/webresult/question.png
cravat/webresult/webresult.py
cravat/webresult/webviewer.yml
cravat/webresult/css/pqselect.min.css
cravat/webresult/fonts/roboto-bold-webfont.woff
cravat/webresult/fonts/roboto-bold-webfont.woff2
cravat/webresult/fonts/roboto-light-webfont.woff
cravat/webresult/fonts/roboto-light-webfont.woff2
cravat/webresult/fonts/roboto-medium-webfont.woff
cravat/webresult/fonts/roboto-medium-webfont.woff2
cravat/webresult/fonts/sourcesanspro-bold-webfont.woff
cravat/webresult/fonts/sourcesanspro-bold-webfont.woff2
cravat/webresult/images/arrow-90deg-down.svg
cravat/webresult/images/arrow-down-right-circle-fill.svg
cravat/webresult/images/arrow-down-right-circle.svg
cravat/webresult/images/arrow-down-right.svg
open_cravat.egg-info/PKG-INFO
open_cravat.egg-info/SOURCES.txt
open_cravat.egg-info/dependency_links.txt
open_cravat.egg-info/entry_points.txt
open_cravat.egg-info/requires.txt
open_cravat.egg-info/top_level.txt
