Metadata-Version: 2.1
Name: open-cravat
Version: 2.16.0
Summary: OpenCRAVAT - variant analysis toolkit
Home-page: https://www.opencravat.org
Author: Kyle Moad, Kyle Anderson, Madison Larsen, Jeltje van Baren, and Rachel Karchin
Author-email: support@opencravat.org
Requires-Python: >=3.9
License-File: LICENSE
